pyframework/__init__.py
pyframework/camera.py
pyframework/color.py
pyframework/image.py
pyframework/internals.py
pyframework/tilemap.py
pyframework/utils.py
ghart_pygame_framework-0.0.3.dist-info/LICENSE
ghart_pygame_framework-0.0.3.dist-info/METADATA
ghart_pygame_framework-0.0.3.dist-info/WHEEL
ghart_pygame_framework-0.0.3.dist-info/top_level.txt
ghart_pygame_framework-0.0.3.dist-info/RECORD
