Metadata-Version: 2.1
Name: ghart-pygame-framework
Version: 0.0.3
Summary: A small framework for pygame
Home-page: https://github.com/graham-hart/pygame-framework
Author: Graham Hart
Author-email: graham@harts.net
License: UNKNOWN
Project-URL: Bug Tracker, https://github.com/graham-hart/pygame-framework/issues
Platform: UNKNOWN
Classifier: Programming Language :: Python :: 3
Classifier: License :: OSI Approved :: MIT License
Classifier: Operating System :: OS Independent
Requires-Python: >=3.8
License-File: LICENSE
Requires-Dist: pygame
